vcat/__init__.py
vcat/cli.py
vcat-0.1.6.dist-info/METADATA
vcat-0.1.6.dist-info/WHEEL
vcat-0.1.6.dist-info/entry_points.txt
vcat-0.1.6.dist-info/top_level.txt
vcat-0.1.6.dist-info/RECORD
